pelican/plugins/liquid_tags/__init__.py
pelican/plugins/liquid_tags/audio.py
pelican/plugins/liquid_tags/b64img.py
pelican/plugins/liquid_tags/content/test_data/main.c
pelican/plugins/liquid_tags/content/test_data/main_cz.c
pelican/plugins/liquid_tags/diag.py
pelican/plugins/liquid_tags/flickr.py
pelican/plugins/liquid_tags/generic.py
pelican/plugins/liquid_tags/giphy.py
pelican/plugins/liquid_tags/gram.py
pelican/plugins/liquid_tags/graphviz.py
pelican/plugins/liquid_tags/img.py
pelican/plugins/liquid_tags/include_code.py
pelican/plugins/liquid_tags/liquid_tags.py
pelican/plugins/liquid_tags/literal.py
pelican/plugins/liquid_tags/mdx_liquid_tags.py
pelican/plugins/liquid_tags/notebook.py
pelican/plugins/liquid_tags/pelicanhtml_1.tpl
pelican/plugins/liquid_tags/pelicanhtml_2.tpl
pelican/plugins/liquid_tags/pelicanhtml_3.tpl
pelican/plugins/liquid_tags/pygalcharts.py
pelican/plugins/liquid_tags/soundcloud.py
pelican/plugins/liquid_tags/speakerdeck.py
pelican/plugins/liquid_tags/spotify.py
pelican/plugins/liquid_tags/test_audio.py
pelican/plugins/liquid_tags/test_data/content/notebooks/test_nbformat3.ipynb
pelican/plugins/liquid_tags/test_data/content/notebooks/test_nbformat4.ipynb
pelican/plugins/liquid_tags/test_data/content/test-generic-config-tag.md
pelican/plugins/liquid_tags/test_data/content/test-ipython-notebook-nbformat3.md
pelican/plugins/liquid_tags/test_data/content/test-ipython-notebook-nbformat4.md
pelican/plugins/liquid_tags/test_data/flickr.json
pelican/plugins/liquid_tags/test_data/giphy.json
pelican/plugins/liquid_tags/test_data/output/index.html
pelican/plugins/liquid_tags/test_data/output/test-ipython-notebook-nb-format-3.html
pelican/plugins/liquid_tags/test_data/output/test-ipython-notebook-nb-format-4.html
pelican/plugins/liquid_tags/test_data/pelicanconf.py
pelican/plugins/liquid_tags/test_flickr.py
pelican/plugins/liquid_tags/test_generation.py
pelican/plugins/liquid_tags/test_generic.py
pelican/plugins/liquid_tags/test_giphy.py
pelican_liquid_tags-1.0.4.dist-info/WHEEL
pelican_liquid_tags-1.0.4.dist-info/METADATA
pelican_liquid_tags-1.0.4.dist-info/RECORD
